[
    {
        "id": "1",
        "userName": "yoske",
        "email": "yos",
        "age": 23,
        "img": "aaa"
    },

    {
        "id": "2",
        "userName": "chaim",
        "email": "yoske",
        "age": 25,
        "img": "bbb"
    },
    {
        "id": "3",
        "userName": "isreal",
        "email": "yos",
        "age": 23,
        "img": "aaa"
    },

    {
        "id": "4",
        "userName": "meair",
        "email": "yoske",
        "age": 25,
        "img": "bbb"
    }
]